telediff/__about__.py
telediff/__init__.py
telediff/__main__.py
telediff/util.py
telediff-1.2.dist-info/METADATA
telediff-1.2.dist-info/WHEEL
telediff-1.2.dist-info/entry_points.txt
telediff-1.2.dist-info/licenses/LICENSE
telediff-1.2.dist-info/RECORD
