Metadata-Version: 2.4
Name: telediff
Version: 1.2
Author-email: Artiom Mocrenco <artiom.mocrenco@gmail.com>
License-Expression: MIT
License-File: LICENSE
Classifier: Development Status :: 4 - Beta
Classifier: Programming Language :: Python :: 3.13
Requires-Python: >=3.8
Requires-Dist: apprise==1.9.6
Requires-Dist: platformdirs==4.4.0
